np_config-0.4.34.dist-info/METADATA
np_config-0.4.34.dist-info/WHEEL
np_config/__init__.py
np_config/config.py
np_config/rigs.py
np_config/utils.py
np_config-0.4.34.dist-info/RECORD
