Metadata-Version: 2.1
Name: np-config
Version: 0.4.34
Summary: Config fetching from file or Zookeeper - with local backup - repackaging code from AIBS mpeconfig.
Author-Email: Ben Hardcastle <ben.hardcastle@alleninstitute.org>, Ross Hytnen <rossh@alleninstitute.org>, Ben Sutton <ben.sutton@alleninstitute.org>
Maintainer-Email: Ben Hardcastle <ben.hardcastle@alleninstitute.org>
Classifier: Programming Language :: Python :: 3
Classifier: License :: OSI Approved :: MIT License
Classifier: Operating System :: OS Independent
Project-URL: Repository, https://github.com/alleninstitute/np_config
Project-URL: Bug tracker, https://github.com/alleninstitute/np_config/issues
Requires-Python: <4.0,>=3.7
Requires-Dist: kazoo~=2.8
Requires-Dist: pyyaml<7,>=5
Requires-Dist: typing-extensions>=4
Requires-Dist: requests<3,>=2
Requires-Dist: backports-cached-property
Requires-Dist: singledispatch<5.0.0,>=4.0.0
Requires-Dist: types-singledispatch<5.0.0.0,>=4.0.0.1
Requires-Dist: platformdirs<4.0.0,>=3.11.0
